opennutgraf/__init__.py
opennutgraf/article_extractor.py
opennutgraf/client.py
opennutgraf/llm_service.py
opennutgraf/models.py
opennutgraf/py.typed
opennutgraf-1.0.0.dist-info/licenses/LICENSE
opennutgraf-1.0.0.dist-info/METADATA
opennutgraf-1.0.0.dist-info/WHEEL
opennutgraf-1.0.0.dist-info/top_level.txt
opennutgraf-1.0.0.dist-info/RECORD
