Metadata-Version: 2.4
Name: opennutgraf
Version: 1.0.0
Summary: A Python library for article extraction and AI-powered summarization
Author-email: Nutgraf Team <team@nutgraf.com>
Maintainer-email: Nutgraf Team <team@nutgraf.com>
License: MIT
Project-URL: Homepage, https://github.com/nutgraf/opennutgraf
Project-URL: Documentation, https://github.com/nutgraf/opennutgraf#readme
Project-URL: Repository, https://github.com/nutgraf/opennutgraf.git
Project-URL: Bug Tracker, https://github.com/nutgraf/opennutgraf/issues
Project-URL: Changelog, https://github.com/nutgraf/opennutgraf/blob/main/CHANGELOG.md
Keywords: article extraction,summarization,AI,LLM,OpenAI,Anthropic,content processing,web scraping
Classifier: Development Status :: 4 - Beta
Classifier: Intended Audience :: Developers
Classifier: License :: OSI Approved :: MIT License
Classifier: Operating System :: OS Independent
Classifier: Programming Language :: Python :: 3
Classifier: Programming Language :: Python :: 3.8
Classifier: Programming Language :: Python :: 3.9
Classifier: Programming Language :: Python :: 3.10
Classifier: Programming Language :: Python :: 3.11
Classifier: Programming Language :: Python :: 3.12
Classifier: Topic :: Software Development :: Libraries :: Python Modules
Classifier: Topic :: Text Processing
Classifier: Topic :: Scientific/Engineering :: Artificial Intelligence
Classifier: Topic :: Internet :: WWW/HTTP :: Indexing/Search
Requires-Python: >=3.8
License-File: LICENSE
Requires-Dist: requests>=2.31.0
Requires-Dist: beautifulsoup4>=4.12.2
Requires-Dist: readability-lxml>=0.8.1
Requires-Dist: openai>=1.35.0
Requires-Dist: anthropic>=0.8.1
Requires-Dist: lxml_html_clean>=0.4.0
Provides-Extra: dev
Requires-Dist: pytest>=6.0; extra == "dev"
Requires-Dist: pytest-cov>=2.0; extra == "dev"
Requires-Dist: black>=22.0; extra == "dev"
Requires-Dist: flake8>=4.0; extra == "dev"
Requires-Dist: mypy>=0.900; extra == "dev"
Requires-Dist: build>=0.7.0; extra == "dev"
Requires-Dist: twine>=4.0.0; extra == "dev"
Provides-Extra: test
Requires-Dist: pytest>=6.0; extra == "test"
Requires-Dist: pytest-cov>=2.0; extra == "test"
Requires-Dist: pytest-mock>=3.0; extra == "test"
Requires-Dist: responses>=0.20.0; extra == "test"
Dynamic: license-file
